LICENSE
MANIFEST.in
README.md
setup.py
zaifer/__init__.py
zaifer.egg-info/PKG-INFO
zaifer.egg-info/SOURCES.txt
zaifer.egg-info/dependency_links.txt
zaifer.egg-info/requires.txt
zaifer.egg-info/top_level.txt
zaifer/zaifapi/connection.py
zaifer/zaifapi/exception.py
zaifer/zaifapi/method.py
zaifer/zaifapi/utils.py