Metadata-Version: 2.1
Name: zaifer
Version: 1.2.0
Summary: zaifer is a zaifapi wrapper library. this library make easily to use zaifapi on python.
Home-page: https://github.com/curio184/zaifer
Author: Yusuke Oya
Author-email: curio@antique-cafe.net
License: MIT
Keywords: zaif zaifapi zaif-exchange trade bot
Platform: UNKNOWN
Classifier: Development Status :: 4 - Beta
Classifier: Intended Audience :: Developers
Classifier: License :: OSI Approved :: MIT License
Classifier: Operating System :: OS Independent
Classifier: Programming Language :: Python
Classifier: Programming Language :: Python :: 3
Classifier: Programming Language :: Python :: 3.5
Classifier: Programming Language :: Python :: 3.6
Classifier: Programming Language :: Python :: 3.7
